<annotation>
	<object>
		<name>Varroa</name>
		<difficult>0</difficult>
		<bndbox>
			<xmin>89</xmin>
			<ymin>1527</ymin>
			<xmax>113</xmax>
			<ymax>1551</ymax>
		</bndbox>
	</object>
	<object>
		<name>Varroa</name>
		<difficult>0</difficult>
		<bndbox>
			<xmin>1590</xmin>
			<ymin>1232</ymin>
			<xmax>1617</xmax>
			<ymax>1259</ymax>
		</bndbox>
	</object>
	<object>
		<name>Varroa</name>
		<difficult>0</difficult>
		<bndbox>
			<xmin>79</xmin>
			<ymin>283</ymin>
			<xmax>98</xmax>
			<ymax>307</ymax>
		</bndbox>
	</object>
	<object>
		<name>Varroa</name>
		<difficult>0</difficult>
		<bndbox>
			<xmin>556</xmin>
			<ymin>1259</ymin>
			<xmax>585</xmax>
			<ymax>1290</ymax>
		</bndbox>
	</object>
	<object>
		<name>Varroa</name>
		<difficult>0</difficult>
		<bndbox>
			<xmin>793</xmin>
			<ymin>1034</ymin>
			<xmax>817</xmax>
			<ymax>1059</ymax>
		</bndbox>
	</object>
	<object>
		<name>Varroa</name>
		<difficult>0</difficult>
		<bndbox>
			<xmin>499</xmin>
			<ymin>1610</ymin>
			<xmax>526</xmax>
			<ymax>1638</ymax>
		</bndbox>
	</object>
	<object>
		<name>Varroa</name>
		<difficult>0</difficult>
		<bndbox>
			<xmin>984</xmin>
			<ymin>1139</ymin>
			<xmax>1009</xmax>
			<ymax>1165</ymax>
		</bndbox>
	</object>
	<object>
		<name>Varroa</name>
		<difficult>0</difficult>
		<bndbox>
			<xmin>65</xmin>
			<ymin>1357</ymin>
			<xmax>91</xmax>
			<ymax>1385</ymax>
		</bndbox>
	</object>
	<object>
		<name>Varroa</name>
		<difficult>0</difficult>
		<bndbox>
			<xmin>1396</xmin>
			<ymin>398</ymin>
			<xmax>1414</xmax>
			<ymax>420</ymax>
		</bndbox>
	</object>
	<object>
		<name>Varroa</name>
		<difficult>0</difficult>
		<bndbox>
			<xmin>375</xmin>
			<ymin>1756</ymin>
			<xmax>405</xmax>
			<ymax>1786</ymax>
		</bndbox>
	</object>
	<object>
		<name>Varroa</name>
		<difficult>0</difficult>
		<bndbox>
			<xmin>308</xmin>
			<ymin>773</ymin>
			<xmax>338</xmax>
			<ymax>801</ymax>
		</bndbox>
	</object>
	<object>
		<name>Varroa</name>
		<difficult>0</difficult>
		<bndbox>
			<xmin>1287</xmin>
			<ymin>1037</ymin>
			<xmax>1303</xmax>
			<ymax>1061</ymax>
		</bndbox>
	</object>
	<object>
		<name>Varroa</name>
		<difficult>0</difficult>
		<bndbox>
			<xmin>1118</xmin>
			<ymin>655</ymin>
			<xmax>1144</xmax>
			<ymax>683</ymax>
		</bndbox>
	</object>
	<object>
		<name>Varroa</name>
		<difficult>0</difficult>
		<bndbox>
			<xmin>567</xmin>
			<ymin>1389</ymin>
			<xmax>597</xmax>
			<ymax>1418</ymax>
		</bndbox>
	</object>
	<object>
		<name>Varroa</name>
		<difficult>0</difficult>
		<bndbox>
			<xmin>1495</xmin>
			<ymin>1100</ymin>
			<xmax>1516</xmax>
			<ymax>1120</ymax>
		</bndbox>
	</object>
	<object>
		<name>Varroa</name>
		<difficult>0</difficult>
		<bndbox>
			<xmin>982</xmin>
			<ymin>1470</ymin>
			<xmax>1009</xmax>
			<ymax>1496</ymax>
		</bndbox>
	</object>
	<object>
		<name>Varroa</name>
		<difficult>0</difficult>
		<bndbox>
			<xmin>489</xmin>
			<ymin>1794</ymin>
			<xmax>514</xmax>
			<ymax>1819</ymax>
		</bndbox>
	</object>
	<object>
		<name>Varroa</name>
		<difficult>0</difficult>
		<bndbox>
			<xmin>1474</xmin>
			<ymin>1427</ymin>
			<xmax>1500</xmax>
			<ymax>1454</ymax>
		</bndbox>
	</object>
	<object>
		<name>Varroa</name>
		<difficult>0</difficult>
		<bndbox>
			<xmin>639</xmin>
			<ymin>1439</ymin>
			<xmax>665</xmax>
			<ymax>1467</ymax>
		</bndbox>
	</object>
	<object>
		<name>Varroa</name>
		<difficult>0</difficult>
		<bndbox>
			<xmin>1519</xmin>
			<ymin>1786</ymin>
			<xmax>1546</xmax>
			<ymax>1814</ymax>
		</bndbox>
	</object>
	<object>
		<name>Varroa</name>
		<difficult>0</difficult>
		<bndbox>
			<xmin>968</xmin>
			<ymin>939</ymin>
			<xmax>990</xmax>
			<ymax>960</ymax>
		</bndbox>
	</object>
	<object>
		<name>Varroa</name>
		<difficult>0</difficult>
		<bndbox>
			<xmin>210</xmin>
			<ymin>1206</ymin>
			<xmax>241</xmax>
			<ymax>1238</ymax>
		</bndbox>
	</object>
	<object>
		<name>Varroa</name>
		<difficult>0</difficult>
		<bndbox>
			<xmin>1193</xmin>
			<ymin>1458</ymin>
			<xmax>1219</xmax>
			<ymax>1482</ymax>
		</bndbox>
	</object>
	<object>
		<name>Varroa</name>
		<difficult>0</difficult>
		<bndbox>
			<xmin>1242</xmin>
			<ymin>1640</ymin>
			<xmax>1271</xmax>
			<ymax>1669</ymax>
		</bndbox>
	</object>
	<object>
		<name>Varroa</name>
		<difficult>0</difficult>
		<bndbox>
			<xmin>1222</xmin>
			<ymin>1036</ymin>
			<xmax>1244</xmax>
			<ymax>1055</ymax>
		</bndbox>
	</object>
	<object>
		<name>Varroa</name>
		<difficult>0</difficult>
		<bndbox>
			<xmin>1188</xmin>
			<ymin>1404</ymin>
			<xmax>1217</xmax>
			<ymax>1431</ymax>
		</bndbox>
	</object>
	<object>
		<name>Varroa</name>
		<difficult>0</difficult>
		<bndbox>
			<xmin>866</xmin>
			<ymin>1609</ymin>
			<xmax>894</xmax>
			<ymax>1637</ymax>
		</bndbox>
	</object>
	<object>
		<name>Varroa</name>
		<difficult>0</difficult>
		<bndbox>
			<xmin>812</xmin>
			<ymin>1553</ymin>
			<xmax>839</xmax>
			<ymax>1579</ymax>
		</bndbox>
	</object>
	<object>
		<name>Varroa</name>
		<difficult>0</difficult>
		<bndbox>
			<xmin>1091</xmin>
			<ymin>1673</ymin>
			<xmax>1119</xmax>
			<ymax>1698</ymax>
		</bndbox>
	</object>
	<object>
		<name>Varroa</name>
		<difficult>0</difficult>
		<bndbox>
			<xmin>1442</xmin>
			<ymin>1517</ymin>
			<xmax>1472</xmax>
			<ymax>1547</ymax>
		</bndbox>
	</object>
	<object>
		<name>Varroa</name>
		<difficult>0</difficult>
		<bndbox>
			<xmin>185</xmin>
			<ymin>1634</ymin>
			<xmax>215</xmax>
			<ymax>1661</ymax>
		</bndbox>
	</object>
	<object>
		<name>Varroa</name>
		<difficult>0</difficult>
		<bndbox>
			<xmin>479</xmin>
			<ymin>1497</ymin>
			<xmax>507</xmax>
			<ymax>1527</ymax>
		</bndbox>
	</object>
	<object>
		<name>Varroa</name>
		<difficult>0</difficult>
		<bndbox>
			<xmin>1312</xmin>
			<ymin>1740</ymin>
			<xmax>1339</xmax>
			<ymax>1768</ymax>
		</bndbox>
	</object>
	<object>
		<name>Varroa</name>
		<difficult>0</difficult>
		<bndbox>
			<xmin>865</xmin>
			<ymin>1751</ymin>
			<xmax>892</xmax>
			<ymax>1782</ymax>
		</bndbox>
	</object>
	<object>
		<name>Varroa</name>
		<difficult>0</difficult>
		<bndbox>
			<xmin>1285</xmin>
			<ymin>1533</ymin>
			<xmax>1313</xmax>
			<ymax>1563</ymax>
		</bndbox>
	</object>
	<object>
		<name>Varroa</name>
		<difficult>0</difficult>
		<bndbox>
			<xmin>335</xmin>
			<ymin>1758</ymin>
			<xmax>352</xmax>
			<ymax>1780</ymax>
		</bndbox>
	</object>
	<object>
		<name>Varroa</name>
		<difficult>0</difficult>
		<bndbox>
			<xmin>1368</xmin>
			<ymin>1403</ymin>
			<xmax>1401</xmax>
			<ymax>1434</ymax>
		</bndbox>
	</object>
	<object>
		<name>Varroa</name>
		<difficult>0</difficult>
		<bndbox>
			<xmin>1559</xmin>
			<ymin>1741</ymin>
			<xmax>1590</xmax>
			<ymax>1772</ymax>
		</bndbox>
	</object>
	<object>
		<name>Varroa</name>
		<difficult>0</difficult>
		<bndbox>
			<xmin>926</xmin>
			<ymin>1795</ymin>
			<xmax>953</xmax>
			<ymax>1826</ymax>
		</bndbox>
	</object>
	<object>
		<name>Varroa</name>
		<difficult>0</difficult>
		<bndbox>
			<xmin>1113</xmin>
			<ymin>1657</ymin>
			<xmax>1141</xmax>
			<ymax>1690</ymax>
		</bndbox>
	</object>
	<object>
		<name>Varroa</name>
		<difficult>0</difficult>
		<bndbox>
			<xmin>1274</xmin>
			<ymin>1578</ymin>
			<xmax>1302</xmax>
			<ymax>1608</ymax>
		</bndbox>
	</object>
	<object>
		<name>Varroa</name>
		<difficult>0</difficult>
		<bndbox>
			<xmin>784</xmin>
			<ymin>1826</ymin>
			<xmax>805</xmax>
			<ymax>1844</ymax>
		</bndbox>
	</object>
	<object>
		<name>Varroa</name>
		<difficult>0</difficult>
		<bndbox>
			<xmin>1530</xmin>
			<ymin>1431</ymin>
			<xmax>1557</xmax>
			<ymax>1462</ymax>
		</bndbox>
	</object>
	<object>
		<name>Varroa</name>
		<difficult>0</difficult>
		<bndbox>
			<xmin>964</xmin>
			<ymin>1811</ymin>
			<xmax>985</xmax>
			<ymax>1834</ymax>
		</bndbox>
	</object>
	<object>
		<name>Varroa</name>
		<difficult>0</difficult>
		<bndbox>
			<xmin>1217</xmin>
			<ymin>1808</ymin>
			<xmax>1245</xmax>
			<ymax>1837</ymax>
		</bndbox>
	</object>
	<object>
		<name>Varroa</name>
		<difficult>0</difficult>
		<bndbox>
			<xmin>101</xmin>
			<ymin>1812</ymin>
			<xmax>143</xmax>
			<ymax>1854</ymax>
		</bndbox>
	</object>
</annotation>